<?xml version="1.0" encoding="utf-8"?>
<!DOCTYPE hibernate-mapping PUBLIC "-//Hibernate/Hibernate Mapping DTD 3.0//EN"
"http://hibernate.sourceforge.net/hibernate-mapping-3.0.dtd">
<!-- 
    Mapping file autogenerated by MyEclipse Persistence Tools
-->
<hibernate-mapping>
    <class name="leo.entity.FamiliRecord" table="FamiliRecord" schema="dbo" catalog="leohis">
        <id name="recordId" type="java.lang.String">
            <column name="RecordID" length="15" />
            <generator class="assigned" />
        </id>
        <property name="medicalInstId" type="java.lang.Boolean">
            <column name="MedicalInstID" />
        </property>
        <property name="province" type="java.lang.String">
            <column name="Province" length="20" />
        </property>
        <property name="prefecture" type="java.lang.String">
            <column name="Prefecture" length="20" />
        </property>
        <property name="town" type="java.lang.String">
            <column name="town" length="20" />
        </property>
        <property name="medicalInstName" type="java.lang.String">
            <column name="MedicalInstName" length="20" />
        </property>
        <property name="agreement" type="java.lang.Boolean">
            <column name="Agreement" />
        </property>
        <property name="mcsId" type="java.lang.Long">
            <column name="MCsID" />
        </property>
        <property name="wcsId" type="java.lang.Long">
            <column name="WCsID" />
        </property>
        <property name="midcardNum" type="java.lang.String">
            <column name="MIDCardNum" length="18" />
        </property>
        <property name="widcardNum" type="java.lang.String">
            <column name="WIDCardNum" length="18" />
        </property>
        <property name="complete" type="java.lang.Boolean">
            <column name="Complete" />
        </property>
        <property name="upload" type="java.lang.Boolean">
            <column name="upload" />
        </property>
        <property name="mopDnId" type="java.lang.String">
            <column name="MOpDnID" length="16" />
        </property>
        <property name="wopDnId" type="java.lang.String">
            <column name="WOpDnID" length="16" />
        </property>
        <property name="prefectureName" type="java.lang.String">
            <column name="PrefectureName" length="100" />
        </property>
        <property name="townName" type="java.lang.String">
            <column name="TownName" length="100" />
        </property>
    </class>
</hibernate-mapping>
