<?xml version='1.0' encoding='UTF-8'?>
<!DOCTYPE hibernate-configuration PUBLIC
          "-//Hibernate/Hibernate Configuration DTD 3.0//EN"
          "http://hibernate.sourceforge.net/hibernate-configuration-3.0.dtd">

<!-- Generated by MyEclipse Hibernate Tools. -->
<hibernate-configuration>
	<session-factory>
		<property name="show_sql">true</property>
		<property name="format_sql">true</property>
		<property name="connection.autocommit">true</property>
		<property name="dialect">
			org.hibernate.dialect.SQLServerDialect
		</property>
		<property name="connection.url">
			jdbc:sqlserver://192.168.1.231:1433;databaseName=leohis
		</property>
		<property name="connection.username">sa</property>
		<property name="connection.password">11</property>
		<property name="connection.driver_class">
			com.microsoft.sqlserver.jdbc.SQLServerDriver
		</property>
		<property name="myeclipse.connection.profile">
			MSSQL2005
		</property>
		<mapping resource="leo/entity/OsfnAuthorityForm.hbm.xml" />
		<mapping resource="leo/entity/OsfnBlocks.hbm.xml" />
		<mapping resource="leo/entity/OsloginRecord.hbm.xml" />
		<mapping resource="leo/entity/OsmedicalInstInfo.hbm.xml" />
		<mapping resource="leo/entity/Osqbn.hbm.xml" />
		<mapping resource="leo/entity/Osstuff.hbm.xml" />
		<mapping resource="leo/entity/OsudefaultFn.hbm.xml" />
		<mapping resource="leo/entity/Osuform.hbm.xml" />
		<mapping resource="leo/entity/OsunitHasS.hbm.xml" />
		<mapping resource="leo/entity/CfacontentFramework.hbm.xml" />
		<mapping resource="leo/entity/Cfcity.hbm.xml" />
		<mapping resource="leo/entity/Cfdhpmodel.hbm.xml" />
		<mapping resource="leo/entity/Cfgroup.hbm.xml" />
		<mapping resource="leo/entity/CfhandleItemDetail.hbm.xml" />
		<mapping resource="leo/entity/Cfmdetail.hbm.xml" />
		<mapping resource="leo/entity/Cfprefecture.hbm.xml" />
		<mapping resource="leo/entity/Cfprovince.hbm.xml" />
		<mapping resource="leo/entity/CfsellInfo.hbm.xml" />
		<mapping resource="leo/entity/Cfstuff.hbm.xml" />
		<mapping resource="leo/entity/Cftown.hbm.xml" />
		<mapping resource="leo/entity/Cfshedition.hbm.xml" />
		<mapping resource="leo/entity/Cfvillage.hbm.xml" />
		<mapping resource="leo/entity/CfwholeDispose.hbm.xml" />
		<mapping resource="leo/entity/Csconsumer.hbm.xml" />
		<mapping resource="leo/entity/CsefileInfo.hbm.xml" />
		<mapping resource="leo/entity/CsheadShow.hbm.xml" />
		<mapping resource="leo/entity/CsmarriageHistory.hbm.xml" />
		<mapping resource="leo/entity/CsmedicalCard.hbm.xml" />
		<mapping resource="leo/entity/CsmedicalCardDetail.hbm.xml" />
		<mapping resource="leo/entity/GhcostType.hbm.xml" />
		<mapping resource="leo/entity/GhloInvoice.hbm.xml" />
		<mapping resource="leo/entity/GhmrCg.hbm.xml" />
		<mapping resource="leo/entity/Ghrinvoice.hbm.xml" />
		<mapping resource="leo/entity/Ghregister.hbm.xml" />
		<mapping resource="leo/entity/GhregisterDivaricateU.hbm.xml" />
		<mapping resource="leo/entity/GhregisterType.hbm.xml" />
		<mapping resource="leo/entity/GydisinfectPackInstance.hbm.xml" />
		<mapping resource="leo/entity/GydisinfectPackUseRe.hbm.xml" />
		<mapping
			resource="leo/entity/GysupplyDisinfectPackInfo.hbm.xml" />
		<mapping resource="leo/entity/SfaccountDetail.hbm.xml" />
		<mapping resource="leo/entity/SfcgTable.hbm.xml" />
		<mapping resource="leo/entity/SfcreditCard.hbm.xml" />
		<mapping resource="leo/entity/SfcsByOtherMethod.hbm.xml" />
		<mapping resource="leo/entity/SfdisposeReturnP.hbm.xml" />
		<mapping resource="leo/entity/SfipdepositRecord.hbm.xml" />
		<mapping resource="leo/entity/SfleaveHospBalance.hbm.xml" />
		<mapping resource="leo/entity/Sfmpreturn.hbm.xml" />
		<mapping resource="leo/entity/Sfopcg.hbm.xml" />
		<mapping resource="leo/entity/SfpadjustRecord.hbm.xml" />
		<mapping resource="leo/entity/SfpreturnItem.hbm.xml" />
		<mapping resource="leo/entity/SfreceiptContent.hbm.xml" />
		<mapping resource="leo/entity/SfreduceItem.hbm.xml" />
		<mapping resource="leo/entity/SfreduceTable.hbm.xml" />
		<mapping resource="leo/entity/Sfscharge.hbm.xml" />
		<mapping resource="leo/entity/SftownAllocate.hbm.xml" />
		<mapping resource="leo/entity/WscontentOfW.hbm.xml" />
		<mapping resource="leo/entity/WsdocW.hbm.xml" />
		<mapping resource="leo/entity/WsdocW1.hbm.xml" />
		<mapping resource="leo/entity/WsdocWframework.hbm.xml" />
		<mapping resource="leo/entity/WsdocWorderFramework.hbm.xml" />
		<mapping resource="leo/entity/Wsdocument.hbm.xml" />
		<mapping resource="leo/entity/WsidocW.hbm.xml" />
		<mapping resource="leo/entity/WsorderItem.hbm.xml" />
		<mapping resource="leo/entity/WsvisitRemind.hbm.xml" />
		<mapping resource="leo/entity/Yfaitem.hbm.xml" />
		<mapping resource="leo/entity/YfapproveItem.hbm.xml" />
		<mapping resource="leo/entity/YfapproveTable.hbm.xml" />
		<mapping resource="leo/entity/YfcheckRecord.hbm.xml" />
		<mapping resource="leo/entity/YfcheckRecordItem.hbm.xml" />
		<mapping resource="leo/entity/YfexbankAitem.hbm.xml" />
		<mapping resource="leo/entity/YfinbankAitem.hbm.xml" />
		<mapping resource="leo/entity/YfinbankTypeSetting.hbm.xml" />
		<mapping resource="leo/entity/YfmalertInventory.hbm.xml" />
		<mapping resource="leo/entity/Yfmalias.hbm.xml" />
		<mapping resource="leo/entity/YfmdosageType.hbm.xml" />
		<mapping resource="leo/entity/YfmdosageUnit.hbm.xml" />
		<mapping resource="leo/entity/YfmexbankA.hbm.xml" />
		<mapping resource="leo/entity/YfminbankA.hbm.xml" />
		<mapping resource="leo/entity/Yfminfo.hbm.xml" />
		<mapping resource="leo/entity/Yfmmanufacturer.hbm.xml" />
		<mapping resource="leo/entity/Yfmstock.hbm.xml" />
		<mapping resource="leo/entity/Yfmsupplier.hbm.xml" />
		<mapping resource="leo/entity/Yfmtype.hbm.xml" />
		<mapping resource="leo/entity/YfmwayTo.hbm.xml" />
		<mapping resource="leo/entity/Yfprice.hbm.xml" />
		<mapping resource="leo/entity/YfsetExbankType.hbm.xml" />
		<mapping resource="leo/entity/Zybed.hbm.xml" />
		<mapping resource="leo/entity/ZydoctorAdvice.hbm.xml" />
		<mapping resource="leo/entity/Zyipmedicine.hbm.xml" />
		<mapping resource="leo/entity/ZyippresExecute.hbm.xml" />
		<mapping resource="leo/entity/Zyipteatment.hbm.xml" />
		<mapping resource="leo/entity/ZyiptreatmentExecute.hbm.xml" />
		<mapping resource="leo/entity/Zyinpatient.hbm.xml" />
		<mapping resource="leo/entity/ZynurseGrade.hbm.xml" />
		<mapping resource="leo/entity/ZyredudancyConsume.hbm.xml" />
		<mapping resource="leo/entity/MzopDn.hbm.xml" />
		<mapping resource="leo/entity/Czacontent.hbm.xml" />
		<mapping resource="leo/entity/CzbcultrasoundIs.hbm.xml" />
		<mapping resource="leo/entity/CzbcultrasoundImage.hbm.xml" />
		<mapping resource="leo/entity/Czdispose.hbm.xml" />
		<mapping resource="leo/entity/CzdisposeDivaricateU.hbm.xml" />
		<mapping resource="leo/entity/CzdisposeItemDescribe.hbm.xml" />
		<mapping resource="leo/entity/CznkendIs.hbm.xml" />
		<mapping resource="leo/entity/CznkendImage.hbm.xml" />
		<mapping resource="leo/entity/CzshbioIsre.hbm.xml" />
		<mapping resource="leo/entity/CzshbioIsterm.hbm.xml" />
		<mapping resource="leo/entity/CfmedicalInst.hbm.xml" />
		<mapping resource="leo/entity/WsstorageLocation.hbm.xml" />
		<mapping resource="leo/entity/Zymadministration.hbm.xml" />
		<mapping resource="leo/entity/ZydoctorAdviceLongTerm.hbm.xml" />
		<mapping resource="leo/entity/SfmzinvoiceContent.hbm.xml" />
		<mapping resource="leo/entity/SfmzinvoiceHead.hbm.xml" />
		<mapping resource="leo/entity/CzmilkGlandIs.hbm.xml" />
		<mapping resource="leo/entity/CzmilkGlandImage.hbm.xml" />
		<mapping resource="leo/entity/SfzyinvoiceContent.hbm.xml" />
		<mapping resource="leo/entity/SfzyinvoiceHead.hbm.xml" />
		<mapping resource="leo/entity/Zydischarge.hbm.xml" />
		<mapping resource="leo/entity/CzdisposalType.hbm.xml" />
		<mapping resource="leo/entity/LeucorrheaTest.hbm.xml" />
		<mapping resource="leo/entity/WifeHepatitisB.hbm.xml" />
		<mapping resource="leo/entity/WifeLiverAndKidney.hbm.xml" />
		<mapping resource="leo/entity/EarlyPregnancyVisit.hbm.xml" />
		<mapping resource="leo/entity/HusClinicalOthers.hbm.xml" />
		<mapping resource="leo/entity/CsconsumerInfo.hbm.xml" />
		<mapping resource="leo/entity/Yqaccount.hbm.xml" />
		<mapping resource="leo/entity/Agreement.hbm.xml" />
		<mapping resource="leo/entity/HusRoutineUrine.hbm.xml" />
		<mapping resource="leo/entity/WifeGeneralSelf.hbm.xml" />
		<mapping resource="leo/entity/TorchandSyphilis.hbm.xml" />
		<mapping resource="leo/entity/DataSourceConfig.hbm.xml" />
		<mapping resource="leo/entity/HusHepatitisB.hbm.xml" />
		<mapping resource="leo/entity/WifeClinicalOthers.hbm.xml" />
		<mapping resource="leo/entity/WifeGeneralDoc.hbm.xml" />
		<mapping resource="leo/entity/BloodCellTest.hbm.xml" />
		<mapping resource="leo/entity/HusLiverAndKidney.hbm.xml" />
		<mapping resource="leo/entity/BirthDefects.hbm.xml" />
		<mapping resource="leo/entity/WifeBodyGeneral.hbm.xml" />
		<mapping resource="leo/entity/FamiliRecord.hbm.xml" />
		<mapping resource="leo/entity/WifeRoutineUrine.hbm.xml" />
		<mapping resource="leo/entity/HusGeneralDoc.hbm.xml" />
		<mapping resource="leo/entity/WomanBc.hbm.xml" />
		<mapping resource="leo/entity/HusOthersTest.hbm.xml" />
		<mapping resource="leo/entity/WifeOthersTest.hbm.xml" />
		<mapping resource="leo/entity/HusBodyGeneral.hbm.xml" />
		<mapping resource="leo/entity/WifeBloodSuger.hbm.xml" />
		<mapping resource="leo/entity/HusGeneralSelf.hbm.xml" />
		<mapping resource="leo/entity/FamiliRecordBasicInfo.hbm.xml" />
		<mapping resource="leo/entity/PregnancyResult.hbm.xml" />
		<mapping resource="leo/entity/HusBloodGroup.hbm.xml" />
		<mapping resource="leo/entity/HusBodyDoc.hbm.xml" />
		<mapping resource="leo/entity/HusSyphilis.hbm.xml" />
		<mapping resource="leo/entity/WifeBodyDoc.hbm.xml" />
		<mapping resource="leo/entity/ThyroidGlandTest.hbm.xml" />
		<mapping resource="leo/entity/WifeBloodGroup.hbm.xml" />
		<mapping resource="leo/entity/Notify.hbm.xml" />
		<mapping resource="leo/entity/HealthyPregnantSms.hbm.xml" />
		<mapping resource="leo/entity/SuccessfulSms.hbm.xml" />
		<mapping resource="leo/entity/OfflineProblem.hbm.xml" />
		<mapping resource="leo/entity/OfflineProblemInvitation.hbm.xml" />
		<mapping resource="leo/entity/NotifyItems.hbm.xml" />
		<mapping resource="leo/entity/News.hbm.xml" />
		<mapping resource="leo/entity/CustomSmsRecord.hbm.xml" />
		<mapping resource="leo/entity/SmsModule.hbm.xml" />
		<mapping resource="leo/entity/NotifyModuleTerm.hbm.xml" />
		<mapping resource="leo/entity/SmsModuleTerm.hbm.xml" />
		<mapping resource="leo/entity/NotifyModule.hbm.xml" />
		<mapping resource="leo/entity/EugenicsModule.hbm.xml" />
		<mapping resource="leo/entity/CzcolposcopeImage.hbm.xml" />
		<mapping resource="leo/entity/CzcolposcopeIs.hbm.xml" />
	</session-factory>
</hibernate-configuration>